aws/osml/integ/http_centerpoint/__init__.py
aws/osml/integ/http_centerpoint/test_http_centerpoint_model.py
aws/osml/integ/sm_aircraft/__init__.py
aws/osml/integ/sm_aircraft/test_sm_aircraft_model.py
aws/osml/integ/sm_centerpoint/__init__.py
aws/osml/integ/sm_centerpoint/test_sm_centerpoint_model.py
aws/osml/integ/sm_flood/__init__.py
aws/osml/integ/sm_flood/test_sm_flood_model.py
aws/osml/integ/sm_multi-container/__init__.py
aws/osml/integ/sm_multi-container/test_sm_multi-container_model.py
aws/osml/load/__init__.py
aws/osml/load/load_test.py
aws/osml/process_image/__init__.py
aws/osml/process_image/test_process_image.py
aws/osml/utils/__init__.py
aws/osml/utils/clients.py
aws/osml/utils/integ_utils.py
aws/osml/utils/osml_config.py
osml_model_runner_test-2.1.0.dist-info/licenses/LICENSE
osml_model_runner_test-2.1.0.dist-info/METADATA
osml_model_runner_test-2.1.0.dist-info/WHEEL
osml_model_runner_test-2.1.0.dist-info/top_level.txt
osml_model_runner_test-2.1.0.dist-info/RECORD
