Metadata-Version: 2.4
Name: osml-model-runner-test
Version: 2.1.0
Summary: Package to run tests against osml-model-runner deployments.
Author: Amazon Web Services
Author-email: aws-osml-admin@amazon.com
License: 
Project-URL: Source, https://github.com/aws-solutions-library-samples/osml-model-runner-test
Project-URL: Tracker, https://github.com/aws-solutions-library-samples/osml-model-runner-test/issues
Classifier: Programming Language :: Python :: 3
Classifier: Operating System :: OS Independent
Requires-Python: >=3.9
License-File: LICENSE
Requires-Dist: boto3==1.28.57
Requires-Dist: botocore==1.31.57
Requires-Dist: geojson==3.2.0
Requires-Dist: pytest==7.3.1
Requires-Dist: setuptools==68.0.0
Requires-Dist: toml==0.10.2
Requires-Dist: locust>=2.32.0
Provides-Extra: gdal
Requires-Dist: gdal>=3.7.0; extra == "gdal"
Provides-Extra: test
Requires-Dist: tox; extra == "test"
Dynamic: license-file
